django_admin_generator/__about__.py
django_admin_generator/__init__.py
django_admin_generator/management/__init__.py
django_admin_generator/management/commands/__init__.py
django_admin_generator/management/commands/admin_generator.py
test_project/__init__.py
test_project/manage.py
test_project/settings.py
test_project/test_commands.py
test_project/urls.py
test_project/wsgi.py
test_project/test_app/__init__.py
test_project/test_app/models.py
test_project/test_app/tests.py
test_project/test_app/views.py
test_project/test_app/migrations/0001_initial.py
test_project/test_app/migrations/__init__.py
test_project/test_app/sub_models/__init__.py
test_project/test_app/sub_models/eggs.py
test_project/test_app/sub_models/meat.py
test_project/test_app/sub_models/models.py
django_admin_generator-2.6.0.dist-info/METADATA
django_admin_generator-2.6.0.dist-info/WHEEL
django_admin_generator-2.6.0.dist-info/top_level.txt
django_admin_generator-2.6.0.dist-info/RECORD
