Metadata-Version: 2.1
Name: django-admin-generator
Version: 2.6.0
Summary: Django Admin Generator is a management command to automatically generate a Django `admin.py` file for given apps/models.
Home-page: https://github.com/WoLpH/django-admin-generator/
Author: Rick van Hattem
Author-email: Wolph@Wol.ph
License: BSD
Classifier: Development Status :: 5 - Production/Stable
Classifier: Environment :: Web Environment
Classifier: Intended Audience :: Developers
Classifier: License :: OSI Approved :: BSD License
Classifier: Natural Language :: English
Classifier: Programming Language :: Python :: 3.7
Classifier: Programming Language :: Python :: 3.8
Classifier: Programming Language :: Python :: 3.9
Classifier: Programming Language :: Python :: 3.10
Classifier: Programming Language :: Python :: 3.11
Provides-Extra: docs
Provides-Extra: tests
